Metadata-Version: 2.1
Name: colcon-bundle
Version: 0.1.3
Summary: Plugin to bundle built software for the colcon command line tool
Home-page: UNKNOWN
Author: Matthew Murphy
Author-email: matmur@amazon.com
Maintainer: Matthew Murphy
Maintainer-email: matmur@amazon.com
License: Apache License, Version 2.0
Project-URL: Changelog, https://github.com/colcon/colcon-bundle/milestones?direction=desc&sort=due_date&state=closed
Project-URL: GitHub, https://github.com/colcon/colcon-bundle/
Keywords: colcon
Platform: UNKNOWN
Classifier: Development Status :: 3 - Alpha
Classifier: Environment :: Console
Classifier: Intended Audience :: Developers
Classifier: License :: OSI Approved :: Apache Software License
Classifier: Operating System :: MacOS
Classifier: Operating System :: Microsoft :: Windows
Classifier: Operating System :: POSIX
Classifier: Programming Language :: Python
Classifier: Topic :: Software Development :: Build Tools
Requires-Python: >=3.5
Requires-Dist: colcon-core (>=0.3.15)
Requires-Dist: colcon-bash (>=0.4.2)
Requires-Dist: colcon-python-setup-py (>=0.2.1)
Requires-Dist: jinja2 (>=2.9.0)
Requires-Dist: setuptools (>=30.3.0)
Requires-Dist: distro (>=1.2.0)
